{
  "$schema": "https://mintlify.com/docs.json",
  "name": "pdf2wordx",
  "theme": "almond",
  "colors": {
    "primary": "#2673d9",
    "light": "#54b8e9",
    "dark": "#2673d9"
  },
  "favicon": "https://media.brand.dev/91a8f38d-5490-433c-8320-5297ee3f7e5c.png",
  "navbar": {
    "primary": {
      "type": "github",
      "href": "https://github.com/dev2forge/pdf2wordx"
    }
  },
  "footer": {
    "socials": {
      "github": "https://github.com/dev2forge/pdf2wordx"
    }
  },
  "navigation": {
    "groups": [
      {
        "group": "Get Started",
        "pages": [
          "introduction",
          "installation",
          "quickstart"
        ]
      },
      {
        "group": "Using pdf2wordx",
        "pages": [
          "guides/gui-walkthrough",
          "guides/conversion",
          "guides/local-development"
        ]
      },
      {
        "group": "Reference",
        "pages": [
          "reference/configuration",
          "reference/dependencies",
          "reference/troubleshooting",
          "reference/changelog"
        ]
      }
    ]
  }
}
